geckoterminal_py/__init__.py
geckoterminal_py/base_client.py
geckoterminal_py/constants.py
geckoterminal_py/clients/__init__.py
geckoterminal_py/clients/async_client.py
geckoterminal_py/clients/sync_client.py
geckoterminal_py-0.2.5.dist-info/METADATA
geckoterminal_py-0.2.5.dist-info/WHEEL
geckoterminal_py-0.2.5.dist-info/licenses/LICENSE
geckoterminal_py-0.2.5.dist-info/RECORD
