Metadata-Version: 2.4
Name: geckoterminal-py
Version: 0.2.5
Author-email: cardosofede <federico.cardoso.e@gmail.com>
License-File: LICENSE
Requires-Python: >=3.10
Requires-Dist: glom>=24.11.0
Requires-Dist: httpx>=0.28.1
Requires-Dist: pandas>=2.2.3
